sms_broker-3.3.0.dist-info/METADATA
sms_broker-3.3.0.dist-info/WHEEL
sms_broker-3.3.0.dist-info/entry_points.txt
sms_broker-3.3.0.dist-info/licenses/LICENSE
sms_broker/__init__.py
sms_broker/__main__.py
sms_broker/base.py
sms_broker/cli.py
sms_broker/db.py
sms_broker/gateways/__init__.py
sms_broker/gateways/config.py
sms_broker/gateways/gateway.py
sms_broker/gateways/teltonika/__init__.py
sms_broker/gateways/teltonika/config.py
sms_broker/gateways/teltonika/gateway.py
sms_broker/gateways/vonage/__init__.py
sms_broker/gateways/vonage/config.py
sms_broker/gateways/vonage/gateway.py
sms_broker/listener.py
sms_broker/server/__init__.py
sms_broker/server/api/__init__.py
sms_broker/server/api/config.py
sms_broker/server/api/server.py
sms_broker/server/config.py
sms_broker/server/file/__init__.py
sms_broker/server/file/config.py
sms_broker/server/file/server.py
sms_broker/server/server.py
sms_broker/server/tcp/__init__.py
sms_broker/server/tcp/config.py
sms_broker/server/tcp/server.py
sms_broker/server/ui/__init__.py
sms_broker/server/ui/config.py
sms_broker/server/ui/server.py
sms_broker/server/ui/templates/create.html
sms_broker/server/ui/templates/detail.html
sms_broker/server/ui/templates/layout.html
sms_broker/server/ui/templates/list.html
sms_broker/server/ui/templates/login.html
sms_broker/settings.py
sms_broker/statics/__init__.py
sms_broker/statics/favicon.ico
sms_broker/statics/logo.png
sms_broker/worker.py
sms_broker-3.3.0.dist-info/RECORD
